reputation/__init__.py
reputation-0.0.1.dist-info/METADATA
reputation-0.0.1.dist-info/WHEEL
reputation-0.0.1.dist-info/licenses/LICENSE
reputation-0.0.1.dist-info/RECORD
